defgraficos/__init__.py
defgraficos/funcgraficos.py
defgraficos/xfuncgraficos.py
defgraficos-1.2.dist-info/METADATA
defgraficos-1.2.dist-info/WHEEL
defgraficos-1.2.dist-info/top_level.txt
defgraficos-1.2.dist-info/RECORD
