Metadata-Version: 2.1
Name: defgraficos
Version: 1.2
Summary: Libreria usada para generacion de graficos customizados, mediante matplotlib
Home-page: https://dina.concytec.gob.pe/appDirectorioCTI/VerDatosInvestigador.do?id_investigador=12581
Author: Jorge Guerra Guerra
Author-email: jguerra91@gmail.com
License: UNKNOWN
Platform: UNKNOWN
